pytenter/__init__.py
pytenter/pytenter.py
pytenter-0.1.10.dist-info/LICENSE
pytenter-0.1.10.dist-info/METADATA
pytenter-0.1.10.dist-info/WHEEL
pytenter-0.1.10.dist-info/entry_points.txt
pytenter-0.1.10.dist-info/top_level.txt
pytenter-0.1.10.dist-info/RECORD
