Metadata-Version: 2.2
Name: pytenter
Version: 0.1.10
Summary: pdfjinja fork with updated libraries
Home-page: https://github.com/boiledsteak/pytenter
Author: Timothy
Classifier: Programming Language :: Python :: 3
Classifier: License :: OSI Approved :: MIT License
Classifier: Operating System :: OS Independent
Requires-Python: >=3.6
License-File: LICENSE
Requires-Dist: jinja2==3.1.5
Requires-Dist: pdfminer.six==20240706
Requires-Dist: pypdf==5.3.0
Requires-Dist: Pillow==11.1.0
Requires-Dist: reportlab==4.3.1
Requires-Dist: fdfgen==0.16.1
Dynamic: author
Dynamic: classifier
Dynamic: description
Dynamic: description-content-type
Dynamic: home-page
Dynamic: requires-dist
Dynamic: requires-python
Dynamic: summary
